AUTHORS
ChangeLog
Footprints.txt
LICENSE.txt
README.md
main.py
setup.cfg
setup.py
style.css
tabmaker/__init__.py
tabmaker/__main__.py
tabmaker.egg-info/PKG-INFO
tabmaker.egg-info/SOURCES.txt
tabmaker.egg-info/dependency_links.txt
tabmaker.egg-info/entry_points.txt
tabmaker.egg-info/not-zip-safe
tabmaker.egg-info/pbr.json
tabmaker.egg-info/top_level.txt