Metadata-Version: 1.0
Name: tabmaker
Version: 1.0.0
Summary: Generate pretty sheet music from ugly input files
Home-page: https://github.com/chrisnorman7/
Author: Chris Norman
Author-email: chris.norman2@googlemail.com
License: MPL-2
Platform: UNKNOWN
